{"data":[{"id":"927306391068450816","name":"Andrew Kesper","username":"andrew_kesper"},{"id":"2806996914","name":"Tim Stevens","username":"TdotStevens"},{"id":"2764980379","name":"Georgina Piper","username":"GeorginaPiper1"},{"id":"2711375072","name":"Jennifer Bechwati","username":"jenbechwati"},{"id":"1649311770","name":"Adam Kennedy","username":"ShureShotABC"},{"id":"1587587965","name":"Nick Haggarty","username":"NickHaggarty"},{"id":"1582094382","name":"Matt Roberts","username":"ACTcameramatt"},{"id":"1514752100","name":"Political Alert","username":"political_alert"},{"id":"883426626","name":"Michael Roddan","username":"MichaelRoddan"},{"id":"879842808","name":"Lisa Cox","username":"_LisaMCox"},{"id":"861952802","name":"michael brissenden","username":"mpbrissenden"},{"id":"786307086","name":"Matthew Doran","username":"MattDoran91"},{"id":"762572743","name":"Mark Riley","username":"Riley7News"},{"id":"723151752","name":"Greg Jennett","username":"GregJennett"},{"id":"554855266","name":"Nakari Thorpe","username":"nakarithorpe"},{"id":"554720963","name":"Anna Vidot","username":"AnnaVidot"},{"id":"495443549","name":"Kylar Loussikian","username":"kloussikian"},{"id":"492753749","name":"Primrose Riordan","username":"primroseriordan"},{"id":"481707036","name":"Jonathan Lea","username":"JonathanLea10"},{"id":"466216593","name":"Natalie Kotsios","username":"NatalieKotsios"},{"id":"436423425","name":"Daniel Burdon","username":"DBurdon1"},{"id":"424624761","name":"Paul Bongiorno","username":"PaulBongiorno"},{"id":"420135247","name":"Alex Beech","username":"AlexHBeech"},{"id":"414460605","name":"Stephanie Peatling","username":"srpeatling"},{"id":"399962066","name":"Alan Thornhill","username":"PrivateBriefing"},{"id":"391707180","name":"Eliza Borrello","username":"ElizaBorrello"},{"id":"373380976","name":"Luke Stephenson","username":"deaf_soundo"},{"id":"369349553","name":"Jane Norman","username":"janeenorman"},{"id":"361514032","name":"Paul Karp","username":"Paul_Karp"},{"id":"345194355","name":"Judith Ireland","username":"CanberraCamper"},{"id":"323494529","name":"Alex Ellinghausen","username":"ellinghausen"},{"id":"314437348","name":"Kate McClymont","username":"Kate_McClymont"},{"id":"299388047","name":"Ed Johnson","username":"edwardrjohnson"},{"id":"288708450","name":"Brihony Speed","username":"brihonyspeed"},{"id":"287651174","name":"Henry Belot","username":"Henry_Belot"},{"id":"277888803","name":"Lucy Sweeney","username":"lucysween"},{"id":"274300640","name":"Colin Brinsden","username":"brinny56"},{"id":"273774135","name":"Kieran Gilbert","username":"Kieran_Gilbert"},{"id":"270249852","name":"Question Time tweets","username":"LatikaQT"},{"id":"269721794","name":"Tom Iggulden","username":"tomiggulden"},{"id":"264076558","name":"Steven Scott","username":"StevenDScott"},{"id":"258622129","name":"Catalina Flórez","username":"florezcata"},{"id":"255753616","name":"Ben Cubby","username":"bencubby"},{"id":"253330901","name":"Tom Connell","username":"tomwconnell"},{"id":"246506383","name":"Mick Tsikas","username":"Mick_Tsikas"},{"id":"246186918","name":"Rashida Yosufzai","username":"Rashidajourno"},{"id":"236207194","name":"John Durie","username":"John_Durie"},{"id":"226500418","name":"James Vyver","username":"jvyver"},{"id":"224592951","name":"Gareth Hutchens","username":"grhutchens"},{"id":"216893913","name":"Marija Zivic","username":"marija_ziv"},{"id":"213875968","name":"Colin James Bettles","username":"ColinJBettles"},{"id":"196003713","name":"Jack Norton","username":"JackNorton8064"},{"id":"193915480","name":"Richard Lawson","username":"lawsonrg55"},{"id":"188597431","name":"Fleur Anderson","username":"fleur_anderson"},{"id":"188236063","name":"Lanai Scarr","username":"lanai_scarr"},{"id":"187379652","name":"Stephanie Borys","username":"StephieBorys"},{"id":"174925702","name":"Catherine McGrath","username":"CathMcGrath"},{"id":"168981860","name":"Ellen Whinnett","username":"ellenwhinnett"},{"id":"167306586","name":"Michael Pachi","username":"michaelpachi"},{"id":"167281867","name":"Laura Tingle","username":"latingle"},{"id":"166071271","name":"Andrew Greene","username":"AndrewBGreene"},{"id":"165700830","name":"Dennis Atkins","username":"dwabriz"},{"id":"165661785","name":"Nick Butterly","username":"nickbutterly"},{"id":"165660881","name":"Andrew Probyn","username":"andrewprobyn"},{"id":"165655235","name":"Shane Wright","username":"swrighteconomy"},{"id":"150548541","name":"S. Easton","username":"StevieoftheEast"},{"id":"149461866","name":"Julie Doyle","username":"JDoyle73"},{"id":"146765658","name":"Bevan Shields","username":"BevanShields"},{"id":"142951285","name":"Heath Aston","username":"HeathJAston"},{"id":"132712980","name":"Matt Coughlan","username":"CoughlanMatt"},{"id":"130413418","name":"Lane Calcutt","username":"lcalcutt"},{"id":"128182333","name":"Anna Henderson","username":"annajhenderson"},{"id":"127804118","name":"Dan Bourchier","username":"Dan_Bourchier"},{"id":"125539697","name":"Andrew Drummond","username":"a_drumm"},{"id":"125486974","name":"Lenore Taylor","username":"lenoretaylor"},{"id":"118942188","name":"David Crowe","username":"CroweDM"},{"id":"117667331","name":"Dan Conifer","username":"DanConifer"},{"id":"115212095","name":"joe kelly","username":"joekellyoz"},{"id":"99370007","name":"lucy barbour","username":"lucybarbour"},{"id":"97548523","name":"Michael Koziol","username":"michaelkoziol"},{"id":"95091601","name":"Patricia Karvelas","username":"PatsKarvelas"},{"id":"92932393","name":"Susan McDonald","username":"McDonaldSusan"},{"id":"89982972","name":"Matthew Knott","username":"KnottMatthew"},{"id":"86823243","name":"Fran Kelly","username":"frankelly08"},{"id":"77203739","name":"Phillip Hudson","username":"PhillipMHudson"},{"id":"76842602","name":"Samantha Maiden","username":"samanthamaiden"},{"id":"75961380","name":"Rosie Lewis","username":"rosieslewis"},{"id":"74983704","name":"Naomi Woodley","username":"naomiwoodley"},{"id":"71410667","name":"Andrew Tillett","username":"andrewtillett"},{"id":"68640609","name":"Sabra Lane","username":"SabraLane"},{"id":"68128023","name":"Amy Remeikis","username":"AmyRemeikis"},{"id":"67231441","name":"David Lipson","username":"davidlipson"},{"id":"67166472","name":"Michelle Grattan","username":"michellegrattan"},{"id":"66917778","name":"Katharine Murphy","username":"murpharoo"},{"id":"66625609","name":"Michelle Ainsworth","username":"Ainswort"},{"id":"66612373","name":"Chris Uhlmann","username":"CUhlmann"},{"id":"65795755","name":"kym smith","username":"kymbo9"},{"id":"64644122","name":"Tony Wright","username":"tonyowright"},{"id":"64375164","name":"Katina Curtis","username":"katinacurtis"},{"id":"60496760","name":"Josh Butler","username":"JoshButler"},{"id":"59660769","name":"Rachel Baxendale","username":"rachelbaxendale"},{"id":"57181602","name":"LaurieOakes","username":"LaurieOakes"},{"id":"55729485","name":"Sarah Whyte","username":"SarWhyte"},{"id":"52327900","name":"Sharri Markson","username":"SharriMarkson"},{"id":"52320140","name":"Phillip Coorey","username":"PhillipCoorey"},{"id":"52211840","name":"Malcolm Farr","username":"farrm51"},{"id":"52012432","name":"Gabrielle Chan","username":"gabriellechan"},{"id":"50560529","name":"Greg Jericho","username":"GrogsGamut"},{"id":"49942109","name":"Louise Yaxley","username":"louiseyaxley"},{"id":"49859711","name":"Mark Kenny","username":"markgkenny"},{"id":"48927175","name":"Tom McIlroy","username":"TomMcIlroy"},{"id":"47874155","name":"James O'Doherty","username":"jmodoh"},{"id":"46828208","name":"Shalailah Medhora","username":"shalailah"},{"id":"46260680","name":"David Speers","username":"David_Speers"},{"id":"46028458","name":"Fergus Hunter","username":"fergushunter"},{"id":"44535159","name":"Adam Gartrell","username":"adamgartrell"},{"id":"44286651","name":"Mikearoo","username":"mpbowers"},{"id":"43868224","name":"Fiona Willan","username":"Fi_Willan"},{"id":"42859261","name":"Lukas Coch","username":"cochl"},{"id":"40643374","name":"Rohan Thomson","username":"rohanthomson"},{"id":"39675770","name":"Charles Croucher","username":"ccroucher9"},{"id":"39482414","name":"Daniela Ritorto","username":"danielaritorto"},{"id":"39449503","name":"Brett Worthington","username":"BWorthington_"},{"id":"39248787","name":"Stephen Dziedzic","username":"stephendziedzic"},{"id":"39193208","name":"Jacqueline Maley","username":"JacquelineMaley"},{"id":"37881687","name":"Mark Di Stefano","username":"MarkDiStef"},{"id":"37622046","name":"Lauren Gianoli","username":"LaurenGianoli"},{"id":"35690142","name":"Annika Smethurst","username":"annikasmethurst"},{"id":"34865851","name":"Tim Lester","username":"telester"},{"id":"34752409","name":"Peter Martin","username":"1petermartin"},{"id":"33056274","name":"Karen Barlow","username":"KJBar"},{"id":"31077006","name":"Sarah Martin","username":"msmarto"},{"id":"29332626","name":"Peter Logue","username":"pjlogue"},{"id":"28667929","name":"Jared Owens","username":"jaredowens"},{"id":"28097192","name":"Jane Lee","username":"JaneSYLee"},{"id":"27402788","name":"Sally Whyte","username":"sallywhyte"},{"id":"26209392","name":"Sid Maher","username":"sidmaher"},{"id":"25297301","name":"Alice Workman","username":"workmanalice"},{"id":"25036511","name":"Latika M Bourke","username":"latikambourke"},{"id":"25032802","name":"Karen Middleton","username":"KarenMMiddleton"},{"id":"23769966","name":"david wroe","username":"davidwroe"},{"id":"23554400","name":"Kerrie Yaxley","username":"KerrieYaxley"},{"id":"23183563","name":"Lyndal Curtis","username":"lyndalcurtis"},{"id":"22346686","name":"Adrian Wilson","username":"aidowilson"},{"id":"22000661","name":"Paul Osborne","username":"osbornep"},{"id":"21972670","name":"Daniel Hurst","username":"danielhurstbne"},{"id":"21956826","name":"Michael Keating","username":"keating01"},{"id":"21749564","name":"Mark Colvin","username":"Colvinius"},{"id":"21744712","name":"Bridie Jabour","username":"bkjabour"},{"id":"21622115","name":"Brooke Boney","username":"boneybrooke"},{"id":"21548431","name":"Adam Todd","username":"_AdamTodd"},{"id":"21055261","name":"Bernard Keane","username":"BernardKeane"},{"id":"20568173","name":"Jacob Greber","username":"jacobgreber"},{"id":"19853179","name":"Lisa Martin","username":"LMARTI"},{"id":"19053396","name":"Peter Jean","username":"peterdujean"},{"id":"17831767","name":"Laura Jayes","username":"ljayes"},{"id":"17774061","name":"James Massola","username":"jamesmassola"},{"id":"17694439","name":"Ursula Heger","username":"ursulaheger"},{"id":"17673627","name":"Tory Shepherd","username":"ToryShepherd"},{"id":"15351240","name":"Frank Keany","username":"FJKeany"},{"id":"15286106","name":"Phoebe Wearne","username":"PhoebeWearne"},{"id":"14707794","name":"Michael Rowland","username":"mjrowland68"},{"id":"13006932","name":"Josh Taylor","username":"joshgnosis"},{"id":"12098632","name":"Renai LeMay","username":"renailemay"},{"id":"6333122","name":"Jack Snape","username":"jacksongs"},{"id":"1223521","name":"Harley Dennett","username":"harleyd"}]}